{
    "Y_遇水发财": "zhangsan@huixuanjiasu.com",
    "N_奶奶的小农院": "lisi@huixuanjiasu.com",
    "T_天才连一连2": "wangwu@huixuanjiasu.com",
    "B_百味炊烟": "your_email@huixuanjiasu.com",
    "C_猜歌之王": "your_email@huixuanjiasu.com",
    "C_村头菜市场": "your_email@huixuanjiasu.com",
    "D_倒水排排序": "your_email@huixuanjiasu.com",
    "G_改装消消消": "your_email@huixuanjiasu.com",
    "G_根本消不完": "your_email@huixuanjiasu.com",
    "G_GGDT": "your_email@huixuanjiasu.com",
    "J_进场打螺丝": "your_email@huixuanjiasu.com",
    "T_Tile Global Trip-MVP": "your_email@huixuanjiasu.com",
    "W_旺财小店": "your_email@huixuanjiasu.com",
    "W_我不是歌神": "your_email@huixuanjiasu.com",
    "X_消消好运来-MVP": "your_email@huixuanjiasu.com",
    "测试文件": "test@huixuanjiasu.com"
}
